{"version": 0.6, "generator": "Overpass API 0.7.56.9 76e5016d", "osm3s": {"timestamp_osm_base": "2021-06-03T21:11:18Z", "copyright": "The data included in this document is from www.openstreetmap.org. The data is made available under ODbL."}, "elements": [{"type": "node", "id": 3377030400, "lat": -5.8115057, "lon": -35.1818576}, {"type": "node", "id": 4412162992, "lat": -6.0184125, "lon": -35.2523888}, {"type": "node", "id": 5235178869, "lat": -5.9452367, "lon": -35.1659792}, {"type": "node", "id": 5235178870, "lat": -5.9452558, "lon": -35.1659628}, {"type": "node", "id": 5235178871, "lat": -5.945274, "lon": -35.1659842}, {"type": "node", "id": 5235178872, "lat": -5.9452549, "lon": -35.1660006}, {"type": "node", "id": 5329503473, "lat": -6.0184319, "lon": -35.2524507}, {"type": "node", "id": 5329503474, "lat": -6.0185216, "lon": -35.2524666}, {"type": "node", "id": 5329503475, "lat": -6.018636, "lon": -35.2524401}, {"type": "node", "id": 5329503476, "lat": -6.018622, "lon": -35.2523339}, {"type": "node", "id": 5329503477, "lat": -6.0185137, "lon": -35.2524251}, {"type": "node", "id": 6013200873, "lat": -6.0487681, "lon": -35.2971937, "tags": {"amenity": "police", "name": "Pol\u00edcia Rodovi\u00e1ria Estadual", "operator": "Estadual", "police": "traffic_police"}}, {"type": "node", "id": 6135295154, "lat": -5.8115051, "lon": -35.1817913}, {"type": "node", "id": 6135295155, "lat": -5.8115718, "lon": -35.1817973}, {"type": "node", "id": 6135295156, "lat": -5.8115718, "lon": -35.181861}, {"type": "way", "id": 541388528, "nodes": [5235178869, 5235178870, 5235178871, 5235178872, 5235178869], "tags": {"amenity": "police", "building": "yes", "name": "Pol\u00edcia Militar", "police": "traffic_police"}}, {"type": "way", "id": 551924193, "nodes": [4412162992, 5329503473, 5329503477, 5329503474, 5329503475, 5329503476, 4412162992], "tags": {"amenity": "police", "building": "yes", "name": "Pol\u00edcia Rodovi\u00e1ria Federal", "name:pt": "Pol\u00edcia Rodovi\u00e1ria Federal", "police": "traffic_police"}}, {"type": "way", "id": 654742472, "nodes": [3377030400, 6135295154, 6135295155, 6135295156, 3377030400], "tags": {"amenity": "police", "building": "yes", "name": "Pol\u00edcia Rodovi\u00e1ria Estadual", "police": "traffic_police"}}]}